es2/__init__.py
es2/__init__.py.bak
es2/api/__init__.py
es2/api/connection.py
es2/api/grpc.py
es2/cli/es2_keygen.py
es2/crypto/__init__.py
es2/crypto/block.py
es2/crypto/cipher.py
es2/crypto/context.py
es2/crypto/decryptor.py
es2/crypto/encryptor.py
es2/crypto/key_manager.py
es2/crypto/parameter.py
es2/es2_client/__init__.py
es2/es2_client/es2_client.py
es2/index/__init__.py
es2/index/index.py
es2/utils/__init__.py
es2/utils/aes.py
es2/utils/logging_config.py
es2/utils/utils.py
es2/utils/version.py
es2.libs/libcrypto-bdaed0ea.so.1.1.1k
es2.libs/libssl-60250281.so.1.1.1k
evi/__init__.py
evi/evi.cpython-311-x86_64-linux-gnu.so
evi/cli/keygen.py
evi/include/Basic.hpp
evi/include/Constant.h
evi/include/Context.hpp
evi/include/Decryptor.hpp
evi/include/Encryptor.hpp
evi/include/FFT.hpp
evi/include/InternalType.hpp
evi/include/KeyGenerator.hpp
evi/include/Macro.h
evi/include/ModArith.hpp
evi/include/NTT.hpp
evi/include/SecretKeyGenerator.hpp
evi/include/Serialize.hpp
evi/include/Span.hpp
evi/include/Timer.hpp
evi/include/EVI/ComputeBuffer.hpp
evi/include/EVI/Const.hpp
evi/include/EVI/Context.hpp
evi/include/EVI/Decryptor.hpp
evi/include/EVI/EVI.hpp
evi/include/EVI/Encryptor.hpp
evi/include/EVI/Enums.hpp
evi/include/EVI/Evaluator.hpp
evi/include/EVI/Export.hpp
evi/include/EVI/Index.hpp
evi/include/EVI/KeyGenerator.hpp
evi/include/EVI/KeyPack.hpp
evi/include/EVI/Message.hpp
evi/include/EVI/Query.hpp
evi/include/EVI/SealInfo.hpp
evi/include/EVI/SearchResult.hpp
evi/include/EVI/SecretKey.hpp
evi/include/EVI/SingleQuery.hpp
evi/include/EVI/Utils.hpp
evi/include/EVI/Version.hpp
evi/include/EVI/IVF/ClusterDB.hpp
evi/include/EVI/impl/Basic.cuh
evi/include/EVI/impl/CKKSTypes.hpp
evi/include/EVI/impl/ComputeBufferImpl.hpp
evi/include/EVI/impl/Const.hpp
evi/include/EVI/impl/ContextImpl.hpp
evi/include/EVI/impl/DataImpl.hpp
evi/include/EVI/impl/DecryptorImpl.hpp
evi/include/EVI/impl/EncryptorImpl.hpp
es2-1.1.3.dist-info/METADATA
es2-1.1.3.dist-info/WHEEL
es2-1.1.3.dist-info/entry_points.txt
es2-1.1.3.dist-info/RECORD
es2-1.1.3.dist-info/licenses/LICENSE
