Metadata-Version: 2.2
Name: es2
Version: 1.1.3
Summary: A client application for performing encrypted vector search using homomorphic encryption.
Author-Email: cryptolabinc <pypi@cryptolab.co.kr>
License: Proprietary
Classifier: License :: Other/Proprietary License
Requires-Python: <3.14,>=3.9
Requires-Dist: grpcio<=1.74.0,>=1.49.1
Requires-Dist: grpcio-health-checking<=1.74.0,>=1.49.1
Requires-Dist: protobuf<6.0.0,>=5.0.0
Requires-Dist: loguru
Requires-Dist: numpy>=2.0.2
Requires-Dist: tqdm
Requires-Dist: cryptography
Provides-Extra: colab
Requires-Dist: numpy==2.0.2; extra == "colab"
